{
  "vanilla": [
    {
      "rate": 0.3,
      "ttft_p50": 24.333333333333332,
      "ttft_p99": 114.66666666666667,
      "goodput": 0.5627421821231696,
      "fairness": 0.6744745704836185,
      "preemptions": 573
    },
    {
      "rate": 0.4,
      "ttft_p50": 66.33333333333333,
      "ttft_p99": 181.66666666666666,
      "goodput": 0.33064985584232137,
      "fairness": 0.513332220803033,
      "preemptions": 963.3333333333334
    },
    {
      "rate": 0.5,
      "ttft_p50": 102.66666666666667,
      "ttft_p99": 271.6666666666667,
      "goodput": 0.17349754357628372,
      "fairness": 0.5321205375515164,
      "preemptions": 1000
    },
    {
      "rate": 0.6,
      "ttft_p50": 113.0,
      "ttft_p99": 303.0,
      "goodput": 0.11549209055602917,
      "fairness": 0.5529404994821038,
      "preemptions": 1081.6666666666667
    },
    {
      "rate": 0.7,
      "ttft_p50": 150.0,
      "ttft_p99": 363.0,
      "goodput": 0.12386363636363637,
      "fairness": 0.5,
      "preemptions": 1137.3333333333333
    },
    {
      "rate": 0.8,
      "ttft_p50": 156.0,
      "ttft_p99": 384.6666666666667,
      "goodput": 0.084429445875229,
      "fairness": 0.5,
      "preemptions": 1156
    },
    {
      "rate": 0.9,
      "ttft_p50": 181.66666666666666,
      "ttft_p99": 410.0,
      "goodput": 0.08551596586005973,
      "fairness": 0.5,
      "preemptions": 1189.6666666666667
    }
  ],
  "uniform": [
    {
      "rate": 0.3,
      "ttft_p50": 9.333333333333334,
      "ttft_p99": 99.0,
      "goodput": 0.6427946916471506,
      "fairness": 0.9283395678823185,
      "preemptions": 202.66666666666666
    },
    {
      "rate": 0.4,
      "ttft_p50": 8.0,
      "ttft_p99": 97.66666666666667,
      "goodput": 0.641781169273681,
      "fairness": 0.9153493168220949,
      "preemptions": 234.33333333333334
    },
    {
      "rate": 0.5,
      "ttft_p50": 15.666666666666666,
      "ttft_p99": 106.0,
      "goodput": 0.41784262485482,
      "fairness": 0.7375323532665262,
      "preemptions": 702.3333333333334
    },
    {
      "rate": 0.6,
      "ttft_p50": 28.666666666666668,
      "ttft_p99": 128.0,
      "goodput": 0.2993332175616289,
      "fairness": 0.609685873824056,
      "preemptions": 1261
    },
    {
      "rate": 0.7,
      "ttft_p50": 50.666666666666664,
      "ttft_p99": 164.66666666666666,
      "goodput": 0.15213276986793223,
      "fairness": 0.5421973211612774,
      "preemptions": 1676.6666666666667
    },
    {
      "rate": 0.8,
      "ttft_p50": 83.66666666666667,
      "ttft_p99": 236.33333333333334,
      "goodput": 0.07471196975375737,
      "fairness": 0.5595605316272516,
      "preemptions": 1738.6666666666667
    },
    {
      "rate": 0.9,
      "ttft_p50": 103.66666666666667,
      "ttft_p99": 281.3333333333333,
      "goodput": 0.07519034881972994,
      "fairness": 0.5186908609477824,
      "preemptions": 1778.6666666666667
    }
  ],
  "semserve": [
    {
      "rate": 0.3,
      "ttft_p50": 8.0,
      "ttft_p99": 13.333333333333334,
      "goodput": 0.9309161831285725,
      "fairness": 0.9970645145505298,
      "preemptions": 2.6666666666666665
    },
    {
      "rate": 0.4,
      "ttft_p50": 3.3333333333333335,
      "ttft_p99": 11.666666666666666,
      "goodput": 0.927264614011602,
      "fairness": 0.9964922573236198,
      "preemptions": 1.3333333333333333
    },
    {
      "rate": 0.5,
      "ttft_p50": 6.0,
      "ttft_p99": 13.666666666666666,
      "goodput": 0.8718108161660444,
      "fairness": 0.9940802203500518,
      "preemptions": 5
    },
    {
      "rate": 0.6,
      "ttft_p50": 4.0,
      "ttft_p99": 23.666666666666668,
      "goodput": 0.8568958703813475,
      "fairness": 0.9887941381538614,
      "preemptions": 24.333333333333332
    },
    {
      "rate": 0.7,
      "ttft_p50": 5.0,
      "ttft_p99": 34.666666666666664,
      "goodput": 0.8198885674384561,
      "fairness": 0.9711317827096202,
      "preemptions": 40
    },
    {
      "rate": 0.8,
      "ttft_p50": 8.0,
      "ttft_p99": 46.333333333333336,
      "goodput": 0.7969322930742859,
      "fairness": 0.9590058248478657,
      "preemptions": 95
    },
    {
      "rate": 0.9,
      "ttft_p50": 8.0,
      "ttft_p99": 45.0,
      "goodput": 0.7650681753631802,
      "fairness": 0.942183683476058,
      "preemptions": 166.33333333333334
    }
  ]
}